nrepl_lazuli/__init__.py
nrepl_lazuli/bencode.py
nrepl_lazuli/server.py
nrepl_lazuli-0.2.3.dist-info/METADATA
nrepl_lazuli-0.2.3.dist-info/WHEEL
nrepl_lazuli-0.2.3.dist-info/top_level.txt
nrepl_lazuli-0.2.3.dist-info/RECORD
