Metadata-Version: 2.4
Name: nrepl-lazuli
Version: 0.2.3
Summary: A nREPL server to be used with the Lazuli project
Home-page: https://gitlab.com/clj-editors/nrepl-lazuli-python
Author: Maurício Szabo
Author-email: mauricio@szabo.link
Classifier: Development Status :: 2 - Pre-Alpha
Classifier: Intended Audience :: Developers
Classifier: License :: OSI Approved :: MIT License
Classifier: Programming Language :: Python :: 3
Dynamic: author
Dynamic: author-email
Dynamic: classifier
Dynamic: description
Dynamic: home-page
Dynamic: summary
